requests_jwtauth/__init__.py
requests_jwtauth/requests_jwtauth.py
requests_jwtauth-1.0.1.dist-info/LICENSE
requests_jwtauth-1.0.1.dist-info/METADATA
requests_jwtauth-1.0.1.dist-info/WHEEL
requests_jwtauth-1.0.1.dist-info/top_level.txt
requests_jwtauth-1.0.1.dist-info/RECORD
