Metadata-Version: 2.1
Name: requests-jwtauth
Version: 1.0.1
Summary: Authenticator plugins for Requests that support JWT bearer tokens
Author-email: Peter Eichman <peichman@umd.edu>
Maintainer-email: UMD Libraries <lib-ssdr@umd.edu>
Project-URL: Repository, https://github.com/umd-lib/requests-jwtauth
Classifier: Development Status :: 5 - Production/Stable
Classifier: Programming Language :: Python :: 3 :: Only
Classifier: Operating System :: OS Independent
Classifier: License :: OSI Approved :: Apache Software License
Requires-Python: >=3.8
License-File: LICENSE
Requires-Dist: jwcrypto
Requires-Dist: requests
Provides-Extra: test
Requires-Dist: freezegun ; extra == 'test'
Requires-Dist: pytest ; extra == 'test'
Requires-Dist: pytest-cov ; extra == 'test'
